calendario_colombiano/__init__.py
calendario_colombiano/calendario.py
tests/__init__.py
tests/test_calendario.py
calendario_colombiano-0.1.0.dist-info/LICENSE.txt
calendario_colombiano-0.1.0.dist-info/METADATA
calendario_colombiano-0.1.0.dist-info/WHEEL
calendario_colombiano-0.1.0.dist-info/top_level.txt
calendario_colombiano-0.1.0.dist-info/RECORD
